easymatrix/easymatrix.py
easymatrix/__init__.py
easymatrix-1.0.0a1.dist-info/DESCRIPTION.rst
easymatrix-1.0.0a1.dist-info/METADATA
easymatrix-1.0.0a1.dist-info/metadata.json
easymatrix-1.0.0a1.dist-info/RECORD
easymatrix-1.0.0a1.dist-info/top_level.txt
easymatrix-1.0.0a1.dist-info/WHEEL
