Metadata-Version: 2.0
Name: easymatrix
Version: 1.0.0a1
Summary: Operations with matrices
Home-page: UNKNOWN
Author: Francisco Vicent
Author-email: franciscovicent@outlook.com
License: GPL
Keywords: matrix matrices mathematics maths
Platform: UNKNOWN
Classifier: Development Status :: 3 - Alpha
Classifier: Intended Audience :: Developers
Classifier: Topic :: Scientific/Engineering :: Mathematics
Classifier: License :: OSI Approved :: GNU General Public License v2 or later (GPLv2+)
Classifier: Programming Language :: Python :: 2
Classifier: Programming Language :: Python :: 2.6
Classifier: Programming Language :: Python :: 2.7
Classifier: Programming Language :: Python :: 3
Classifier: Programming Language :: Python :: 3.2
Classifier: Programming Language :: Python :: 3.3
Classifier: Programming Language :: Python :: 3.4
